vescale/__init__.py
vescale/__pycache__/__init__.cpython-39.pyc
vescale/checkpoint/README.md
vescale/checkpoint/__init__.py
vescale/checkpoint/load_state_dict.py
vescale/checkpoint/save_state_dict.py
vescale/checkpoint/version.py
vescale/checkpoint/__pycache__/__init__.cpython-39.pyc
vescale/checkpoint/__pycache__/load_state_dict.cpython-39.pyc
vescale/checkpoint/__pycache__/save_state_dict.cpython-39.pyc
vescale/checkpoint/api/base_checkpointer.py
vescale/checkpoint/api/meta_type.py
vescale/checkpoint/api/vescale_checkpointer.py
vescale/checkpoint/api/__pycache__/base_checkpointer.cpython-39.pyc
vescale/checkpoint/api/__pycache__/meta_type.cpython-39.pyc
vescale/checkpoint/api/__pycache__/vescale_checkpointer.cpython-39.pyc
vescale/checkpoint/planner/__init__.py
vescale/checkpoint/planner/common.py
vescale/checkpoint/planner/__pycache__/__init__.cpython-39.pyc
vescale/checkpoint/planner/__pycache__/common.cpython-39.pyc
vescale/checkpoint/planner/vescale/__init__.py
vescale/checkpoint/planner/vescale/vescale_planner.py
vescale/checkpoint/planner/vescale/vescale_planner_helpers.py
vescale/checkpoint/planner/vescale/__pycache__/__init__.cpython-39.pyc
vescale/checkpoint/planner/vescale/__pycache__/vescale_planner.cpython-39.pyc
vescale/checkpoint/planner/vescale/__pycache__/vescale_planner_helpers.cpython-39.pyc
vescale/checkpoint/storage/filesystem.py
vescale/checkpoint/storage/__pycache__/filesystem.cpython-39.pyc
vescale/checkpoint/utilities/bfile.py
vescale/checkpoint/utilities/logger.py
vescale/checkpoint/utilities/mem_checkpoint.py
vescale/checkpoint/utilities/sync_queue.py
vescale/checkpoint/utilities/__pycache__/bfile.cpython-39.pyc
vescale/checkpoint/utilities/__pycache__/logger.cpython-39.pyc
vescale/checkpoint/utilities/__pycache__/mem_checkpoint.cpython-39.pyc
vescale/checkpoint/utilities/server/__init__.py
vescale/checkpoint/utilities/server/detached_mem_server.py
vescale/checkpoint/utilities/server/mem_file_service.proto
vescale-0.0.1.dist-info/LICENSE
vescale-0.0.1.dist-info/METADATA
vescale-0.0.1.dist-info/NOTICE
vescale-0.0.1.dist-info/WHEEL
vescale-0.0.1.dist-info/top_level.txt
vescale-0.0.1.dist-info/RECORD
