Metadata-Version: 2.1
Name: vescale
Version: 0.0.1
Summary: veScale: A PyTorch Native LLM Training Framework
Home-page: 
Author: 
Author-email: ByteDance <vescale-dev@bytedance.com>
Project-URL: Homepage, https://github.com/volcengine/veScale
Project-URL: Documentation, https://github.com/volcengine/veScale/blob/main/README.md
Project-URL: Repository, https://github.com/volcengine/veScale.git
Project-URL: Issues, https://github.com/volcengine/veScale/issues
Classifier: Programming Language :: Python :: 3
Classifier: License :: OSI Approved :: MIT License
Classifier: Operating System :: OS Independent
Requires-Python: >=3.8
License-File: LICENSE
License-File: NOTICE
